sample/__init__.py
sunwoolabs-0.0.2.dist-info/METADATA
sunwoolabs-0.0.2.dist-info/WHEEL
sunwoolabs-0.0.2.dist-info/top_level.txt
sunwoolabs-0.0.2.dist-info/RECORD
